testwizard/commands_audio/WaitForAudioCommand.py
testwizard/commands_audio/WaitForAudioResult.py
testwizard/commands_audio/WaitForPeakAudioCommand.py
testwizard/commands_audio/__init__.py
testwizard.commands_audio-3.8.1.dist-info/LICENSE.txt
testwizard.commands_audio-3.8.1.dist-info/METADATA
testwizard.commands_audio-3.8.1.dist-info/WHEEL
testwizard.commands_audio-3.8.1.dist-info/top_level.txt
testwizard.commands_audio-3.8.1.dist-info/RECORD
