Metadata-Version: 2.1
Name: testwizard.commands-audio
Version: 3.8.1
Summary: Testwizard Audio commands
Home-page: https://www.resillion.com/testwizard/
Author: Resillion - Belgium
Author-email: testwizard-support@resillion.com
License: UNKNOWN
Platform: UNKNOWN
Classifier: Programming Language :: Python :: 3.3
Classifier: Development Status :: 5 - Production/Stable
Classifier: Operating System :: OS Independent
License-File: LICENSE.txt
Requires-Dist: testwizard.commands-core ==3.8.1
